{
  "constraint_algebra": {
    "su2_verification": {
      "closure_verified": true,
      "max_violation": 0.0,
      "violations": [
        {
          "generators": [
            "J_x",
            "J_x"
          ],
          "violation": 0.0
        },
        {
          "generators": [
            "J_x",
            "J_y"
          ],
          "violation": 0.0
        },
        {
          "generators": [
            "J_x",
            "J_z"
          ],
          "violation": 0.0
        },
        {
          "generators": [
            "J_y",
            "J_x"
          ],
          "violation": 0.0
        },
        {
          "generators": [
            "J_y",
            "J_y"
          ],
          "violation": 0.0
        },
        {
          "generators": [
            "J_y",
            "J_z"
          ],
          "violation": 0.0
        },
        {
          "generators": [
            "J_z",
            "J_x"
          ],
          "violation": 0.0
        },
        {
          "generators": [
            "J_z",
            "J_y"
          ],
          "violation": 0.0
        },
        {
          "generators": [
            "J_z",
            "J_z"
          ],
          "violation": 0.0
        }
      ]
    },
    "constraint_closure": {
      "closure_verified": false,
      "violation_summary": {
        "[H, H]": 0.0,
        "[H, G_x]": 0.0,
        "[H, G_y]": 0.0,
        "[H, G_z]": 0.0,
        "[D_x, D_x]": 0.0,
        "[D_x, D_y]": 0.0,
        "[D_x, D_z]": 0.0,
        "[D_y, D_x]": 0.0,
        "[D_y, D_y]": 0.0,
        "[D_y, D_z]": 0.0,
        "[D_z, D_x]": 0.0,
        "[D_z, D_y]": 0.0,
        "[D_z, D_z]": 0.0,
        "[G_x, H]": 0.0,
        "[G_x, G_x]": 0.0,
        "[G_x, G_y]": 0.3945270613006219,
        "[G_x, G_z]": 0.2546687200169307,
        "[G_y, H]": 0.0,
        "[G_y, G_x]": 0.3945270613006219,
        "[G_y, G_y]": 0.0,
        "[G_y, G_z]": 0.1403975104024479,
        "[G_z, H]": 0.0,
        "[G_z, G_x]": 0.2546687200169307,
        "[G_z, G_y]": 0.1403975104024479,
        "[G_z, G_z]": 0.0
      },
      "max_violation": 0.3945270613006219,
      "polymer_corrections_validated": true
    },
    "closure_verified": false,
    "max_violation": 0.3945270613006219,
    "resolution_status": "NEEDS_REFINEMENT",
    "recommendations": [
      "Constraint algebra closure verification failed with max violation: 3.95e-01",
      "Implement numerical stabilization for constraint operator computation",
      "Refine polymer corrections in constraint algebra structure constants",
      "Consider higher precision arithmetic for constraint computations"
    ]
  },
  "polymer_scale": {
    "theoretical_constraints": {
      "planck_scale": 1.616e-35,
      "theoretical_mu": 1.2597615553977474e-34,
      "area_quantum": 2.2615872368652946e-70,
      "volume_quantum": 5.967007659946632e-156,
      "uncertainty_bounds": [
        1.2597615553977474e-35,
        1.2597615553977474e-33
      ]
    },
    "phenomenology_analysis": {
      "energy_enhancement_factors": [
        1.0,
        1.0,
        1.0,
        1.0,
        1.0,
        1.0,
        1.0,
        1.0,
        1.0,
        1.0,
        1.0,
        1.0,
        1.0,
        1.0,
        1.0,
        1.0,
        1.0,
        1.0,
        1.0,
        1.0,
        1.0,
        1.0,
        1.0,
        1.0,
        1.0,
        1.0,
        1.0,
        1.0,
        1.0,
        1.0,
        1.0,
        1.0,
        1.0,
        1.0,
        1.0,
        1.0,
        1.0,
        1.0,
        1.0,
        1.0,
        1.0,
        1.0,
        1.0,
        1.0,
        1.0,
        1.0,
        1.0,
        1.0,
        1.0,
        1.0,
        1.0,
        1.0,
        1.0,
        1.0,
        1.0,
        1.0,
        1.0,
        1.0,
        1.0,
        1.0,
        1.0,
        1.0,
        1.0,
        1.0,
        1.0,
        1.0,
        1.0,
        1.0,
        1.0,
        1.0,
        1.0,
        1.0,
        1.0,
        1.0,
        1.0,
        1.0,
        1.0,
        1.0,
        1.0,
        1.0,
        1.0,
        1.0,
        1.0,
        1.0,
        1.0,
        1.0,
        1.0,
        1.0,
        1.0,
        1.0,
        1.0,
        1.0,
        1.0,
        1.0,
        1.0,
        1.0,
        1.0,
        1.0,
        1.0,
        1.0
      ],
      "warp_metric_corrections": [
        2.443899394945313e+58,
        3.891378955228181e+58,
        6.19617575277935e+58,
        9.866064035667976e+58,
        1.570956400199519e+59,
        2.5014068451267904e+59,
        3.982947078641067e+59,
        6.341978100108218e+59,
        1.0098222604548482e+60,
        1.6079226096550305e+60,
        2.560267504377844e+60,
        4.076669893571236e+60,
        6.491211325665012e+60,
        1.033584410179736e+61,
        1.645758671794763e+61,
        2.6205132150907264e+61,
        4.1725981021119636e+61,
        6.643956161520448e+61,
        1.0579057075701682e+62,
        1.684485055141279e+62,
        2.6821765689417154e+62,
        4.270783599428598e+62,
        6.800295239453361e+62,
        1.0827993099421073e+63,
        1.7241227098623922e+63,
        2.7452909245225397e+63,
        4.371279501832757e+63,
        6.960313135652787e+63,
        1.108278684216606e+64,
        1.7646930791047736e+64,
        2.80989042538668e+64,
        4.4741401755170044e+64,
        7.124096416471916e+64,
        1.1343576142051315e+65,
        1.8062181105942492e+65,
        2.876010018520319e+65,
        4.579421265966412e+65,
        7.291733685258694e+65,
        1.1610502080663207e+66,
        1.8487202685090616e+66,
        2.9436854732479415e+66,
        4.687179728060736e+66,
        7.463315630288391e+66,
        1.1883709059381989e+67,
        1.892222545632523e+67,
        3.0129534005827856e+67,
        4.7974738568864086e+67,
        7.638935073824055e+67,
        1.216334487749997e+68,
        1.9367484757916344e+68,
        3.083851273032647e+68,
        4.910363319272812e+68,
        7.818687022331452e+68,
        1.2449560812177838e+69,
        1.982322146588394e+69,
        3.1564174448717206e+69,
        5.025909186070798e+69,
        8.002668717875571e+69,
        1.2742511700282043e+70,
        2.0289682124306914e+70,
        3.230691172889466e+70,
        5.14417396519075e+70,
        8.19097969072656e+70,
        1.3042356022149989e+71,
        2.0767119078698279e+71,
        3.3067126376277215e+71,
        5.2652216354180565e+71,
        8.383721813203531e+71,
        1.3349255987322105e+72,
        2.1255790612518823e+72,
        3.384522965117528e+72,
        5.38911768102431e+72,
        8.58099935478537e+72,
        1.3663377622295497e+73,
        2.1755961086903132e+73,
        3.4641642491274677e+73,
        5.515929127192925e+73,
        8.78291903851836e+73,
        1.3984890860340402e+74,
        2.2267901083673424e+74,
        3.545679573935513e+74,
        5.645724576278382e+74,
        8.989590098751116e+74,
        1.431396963343081e+75,
        2.2791887551718705e+75,
        3.6291130376367216e+75,
        5.778574244918664e+75,
        9.201124340228104e+75,
        1.4650791966337073e+76,
        2.3328203956818358e+76,
        3.714509775999334e+76,
        5.914550002020997e+76,
        9.41763619857368e+76,
        1.499554007293504e+77,
        2.3877140434991217e+77,
        3.8019159868825246e+77,
        6.053725407641441e+77,
        9.639242802199387e+77,
        1.5348400454779008e+78,
        2.4438993949453138e+78
      ],
      "volume_operator_eigenvalues": [
        0.8660307628525312,
        0.8660321661613981,
        0.866033936936351,
        0.8660361714009135,
        0.8660389909754016,
        0.8660425488748769,
        0.8660470384348189,
        0.8660527036169337,
        0.8660598522659791,
        0.8660688728379816,
        0.8660802555088523,
        0.8660946188104381,
        0.8661127432414076,
        0.8661356136793784,
        0.8661644728989502,
        0.8662008891038069,
        0.8662468411425606,
        0.8663048260389529,
        0.8663779946795792,
        0.8664703230323783,
        0.8665868281998597,
        0.8667338410473592,
        0.8669193502208752,
        0.8671534362483486,
        0.8674488193133453,
        0.8678215504670527,
        0.8682918838388913,
        0.8688853772414815,
        0.8696342809765945,
        0.8705792903095003,
        0.8717717568407896,
        0.8732764789411225,
        0.8751752228805291,
        0.8775711659896493,
        0.8805945032933272,
        0.8844095222798037,
        0.8892235302469162,
        0.895298119335352,
        0.9029633813883928,
        0.9126358450705263,
        0.9248411099440332,
        0.9402424074343109,
        0.9596766406805666,
        0.9841998616694649,
        1.015144656869253,
        1.054192559687177,
        1.1034654246272637,
        1.1656407284002985,
        1.2440970634230242,
        1.343097729791577,
        1.4680224020768664,
        1.6256594596648148,
        1.8245748658084555,
        2.0755776401986834,
        2.3923072187316365,
        2.7919746174740716,
        3.296297675514268,
        3.9326811975912372,
        4.735706125193801,
        5.749008657362758,
        7.027651432208393,
        8.641115618629875,
        10.677076507846483,
        13.246167769557488,
        16.487993261372512,
        20.57871307191821,
        25.740616021549453,
        32.25419878826089,
        40.47340803585532,
        50.844873798292966,
        63.932179258108555,
        80.44648573336319,
        101.28517702822643,
        127.58062307273568,
        160.76171265729315,
        202.63149893719745,
        255.46517694699418,
        322.13371720135456,
        406.2598736052772,
        512.4150431094629,
        646.3676744213607,
        815.3967242470716,
        1028.687194207769,
        1297.8292418200522,
        1637.4479871220938,
        2065.9982384997375,
        2606.767322940251,
        3289.14051429087,
        4150.197822616347,
        5236.72891384115,
        6607.775649968397,
        8337.840410955765,
        10520.934537757728,
        13275.686888043698,
        16751.790102394338,
        21138.134869670608,
        26673.074205758778,
        33657.37550435478,
        42470.564171394784,
        53591.54695265865
      ],
      "holonomy_discretization_errors": [
        4.0023798788789255e-06,
        7.673666613643677e-06,
        -1.7736298193681287e-06,
        -2.051558750364017e-06,
        -1.0831840229544964e-05,
        -6.655202988371294e-06,
        1.2798243516672137e-05,
        3.0964316214362756e-05,
        2.1537702602016793e-05,
        -3.5887854543357514e-05,
        2.7795484744038777e-05,
        -5.015429069847847e-06,
        9.87564222335269e-05,
        6.935872340384214e-05,
        0.00016052045382549402,
        0.00010068430741795521,
        4.620053635668795e-05,
        3.180849481799884e-05,
        -0.0003754430182374019,
        -0.0004546420388277641,
        0.000406618783185549,
        -0.0007500976557223037,
        0.0006068810232039556,
        -7.013467899873956e-05,
        -0.0013188608511495012,
        -0.0013752796128378008,
        -0.001179243903312656,
        0.003267427814767568,
        -0.0007852411120715788,
        -0.005042602845835209,
        0.006397261517283922,
        -0.004753982895227513,
        0.005894867197029887,
        0.011927670954484826,
        -0.00750968891459381,
        0.009036431131918252,
        0.01429004823691483,
        0.019982705496066986,
        -0.014399409185699473,
        0.03789872846572514,
        -0.05136539562748006,
        -0.08470020737746725,
        0.02571678069571163,
        -0.04886963545619311,
        -0.17147558343368335,
        0.13098325453898693,
        -0.21349838859041964,
        0.3321849980250244,
        0.1814819583335014,
        -0.16746152050679464,
        -0.6446352270130093,
        0.8516282332752863,
        0.409499855481971,
        -1.2976441328893304,
        -1.7611155376636662,
        -0.8755828016256374,
        0.9106461752815814,
        1.1907338567376224,
        -2.607021765621305,
        -2.680559116920458,
        -6.713674030286973,
        2.7236739929858222,
        -3.221804597633105,
        -9.168239612154867,
        16.953703967873054,
        -10.631788580827939,
        -28.59678641737483,
        -30.40874980163561,
        -43.89923147667591,
        -35.574842997937004,
        70.1081658722218,
        70.99210880584374,
        111.84187402858485,
        -40.27346131429814,
        -88.91928318416895,
        -229.13935631983375,
        32.40725247155955,
        364.23220921590183,
        -331.14963103657385,
        -236.14359672435612,
        618.9093508609698,
        830.726853996604,
        1186.468791140432,
        669.5614413233046,
        -1727.7764173042426,
        -1336.6717710396565,
        2811.1076746853078,
        3678.051883417342,
        1951.7968428805457,
        -4442.311466271068,
        6276.64017770228,
        -7499.35750297671,
        -1310.8762358144422,
        -7661.132007460214,
        12844.256473780995,
        19241.173602317776,
        -9547.897608173023,
        37662.27207565149,
        46266.91380524945,
        -4591.195331118307
      ],
      "energy_enhancement_factors_sensitivity": 0.0,
      "warp_metric_corrections_sensitivity": 4.674176253326576,
      "volume_operator_eigenvalues_sensitivity": 3.2511513731862838,
      "holonomy_discretization_errors_sensitivity": 6.886667107248313
    },
    "optimization_results": {
      "optimal_mu": 1.1483674108945934e-36,
      "optimization_success": true,
      "objective_value": 4.900565034479154e-05,
      "theoretical_consistency": 0.07106233978308127,
      "uncertainty_factor": 0.0070004035844222256,
      "confidence_interval": [
        1.1403283755551331e-36,
        1.1564064462340536e-36
      ]
    },
    "recommended_mu": 1.1483674108945934e-36,
    "uncertainty_bounds": [
      1.1403283755551331e-36,
      1.1564064462340536e-36
    ],
    "resolution_status": "RESOLVED",
    "validation_metrics": {
      "theoretical_consistency": 0.07106233978308127,
      "observational_compliance": "True"
    }
  },
  "volume_operator": {
    "spectrum_validation": {
      "spectrum_computed": true,
      "stability_analysis": {
        "det_1e-18": {
          "stable_fraction": 0.0,
          "mean_eigenvalue": 7.08318904092163e-113,
          "singular_cases": 1000
        },
        "det_1e-10": {
          "stable_fraction": 1.0,
          "mean_eigenvalue": 2.239901046685595e-110,
          "singular_cases": 0
        },
        "det_1e-05": {
          "stable_fraction": 1.0,
          "mean_eigenvalue": 7.083189040921629e-108,
          "singular_cases": 0
        },
        "det_1e+00": {
          "stable_fraction": 1.0,
          "mean_eigenvalue": 2.2399010466855963e-105,
          "singular_cases": 0
        },
        "det_1e+02": {
          "stable_fraction": 1.0,
          "mean_eigenvalue": 2.239901046685596e-104,
          "singular_cases": 0
        }
      },
      "singular_case_handling": {},
      "polymer_effect_analysis": {}
    },
    "edge_case_handling": {
      "eigenvalues": [
        0.0,
        3.7146045203705493e-112,
        4.8410917133798044e-117,
        1.468877549342498e-112,
        0.0
      ],
      "stability_flags": [
        "False",
        "False",
        "False",
        "False",
        "False"
      ],
      "singular_cases": [
        "Near-singular metric: det(q) = 1e-18",
        "Near-singular metric: det(q) = 1e-18",
        "Near-singular metric: det(q) = 1e-18",
        "Near-singular metric: det(q) = 1e-18",
        "Negative j: -1.0",
        "Near-singular metric: det(q) = 1e-18"
      ],
      "polymer_corrections": [
        1.0,
        0.8860100352633589,
        0.9999999999842528,
        3.0341865766758454e-11,
        1.0
      ],
      "summary": {
        "total_computed": 5,
        "stable_cases": "0",
        "singular_cases_count": 6,
        "mean_eigenvalue": 1.7278434935433938e-112,
        "eigenvalue_range": [
          0.0,
          3.7146045203705493e-112
        ]
      }
    },
    "numerical_stability": {
      "singular_cases_handled": 6,
      "stability_achieved": "False"
    },
    "resolution_status": "RESOLVED",
    "robustness_metrics": {
      "computation_success_rate": 0.0,
      "singular_case_detection": true
    }
  },
  "statistical_coverage": {
    "coverage_validation": {
      "observed_coverage": 0.985,
      "target_coverage": 0.952,
      "coverage_difference": 0.03300000000000003,
      "within_tolerance": false,
      "statistical_test": {
        "z_statistic": 4.881742267164996,
        "p_value": 1.0515263269006425e-06,
        "significant": "True"
      },
      "coverage_confidence_interval": [
        0.9753802999029587,
        0.9915809502499656
      ],
      "summary_statistics": {
        "total_intervals": 1000,
        "covered_count": 985,
        "violation_count": 15,
        "mean_interval_width": 2.0487319140107076,
        "median_interval_width": 1.732491469312446
      },
      "validation_passed": false
    },
    "target_achieved": false,
    "coverage_metrics": {
      "observed_coverage": 0.985,
      "coverage_error": 0.03300000000000003,
      "within_tolerance": false
    },
    "resolution_status": "NEEDS_CALIBRATION"
  },
  "summary": {
    "resolution_timestamp": "2025-07-05T20:57:45.136578",
    "concerns_addressed": 4,
    "resolution_status_summary": {
      "constraint_algebra": "NEEDS_REFINEMENT",
      "polymer_scale": "RESOLVED",
      "volume_operator": "RESOLVED",
      "statistical_coverage": "NEEDS_CALIBRATION"
    },
    "overall_assessment": "REQUIRES_ADDITIONAL_RESOLUTION",
    "critical_findings": [
      "constraint_algebra: NEEDS_REFINEMENT",
      "statistical_coverage: NEEDS_CALIBRATION"
    ],
    "recommendations_for_next_phase": [
      "Address remaining unresolved concerns before controller implementation",
      "Implement refinements for non-resolved issues",
      "Re-run resolution analysis after improvements"
    ]
  }
}